fmga/__init__.py
fmga/fmga_local.py
fmga/function_maximize.py
fmga-2.8.0.dist-info/METADATA
fmga-2.8.0.dist-info/RECORD
fmga-2.8.0.dist-info/WHEEL
fmga-2.8.0.dist-info/top_level.txt
