Metadata-Version: 2.1
Name: fmga
Version: 2.8.0
Summary: Genetic algorithms for n-dimensional function maximization.
Home-page: https://github.com/ameya98/GeneticAlgorithmsRepo/tree/master/fmga
Author: Ameya Daigavane
Author-email: ameya.d.98@gmail.com
License: UNKNOWN
Keywords: genetic,genetic_algorithms
Platform: UNKNOWN
Classifier: Programming Language :: Python :: 3
Classifier: License :: OSI Approved :: MIT License
Classifier: Operating System :: OS Independent
Requires-Dist: numpy
Requires-Dist: pathos (>=0.2.2.1)
